jasmine/__about__.py
jasmine/__init__.py
jasmine/caustics/__init__.py
jasmine/caustics/caustic_creator_cls.py
jasmine/caustics/source_trajectory_creator_cls.py
jasmine/classes_and_files_reader/RTModel_results_cls.py
jasmine/classes_and_files_reader/RTModel_results_reader.py
jasmine/classes_and_files_reader/__init__.py
jasmine/classes_and_files_reader/best_models_wrap_up.py
jasmine/classes_and_files_reader/chi2_per_model_getter.py
jasmine/classes_and_files_reader/datachallenge_lightcurve_cls.py
jasmine/classes_and_files_reader/datachallenge_reader.py
jasmine/classes_and_files_reader/get_initcond.py
jasmine/classes_and_files_reader/gullsrges_lightcurve_cls.py
jasmine/classes_and_files_reader/gullsrges_reader.py
jasmine/classes_and_files_reader/mass_ratio_and_separation_getter.py
jasmine/classes_and_files_reader/new_gullsrges_lightcurve_cls.py
jasmine/classes_and_files_reader/new_gullsrges_reader.py
jasmine/classes_and_files_reader/parallax_getter.py
jasmine/classes_and_files_reader/rtmodel_template_cls.py
jasmine/constants/__init__.py
jasmine/constants/filter_bands.py
jasmine/constants/general_physics_constants.py
jasmine/constants/limb_darkening_parameters.py
jasmine/constants/relative_error.png
jasmine/files_organizer/RTModel_ephemerides_tools.py
jasmine/files_organizer/__init__.py
jasmine/files_organizer/data_challenge_prep.py
jasmine/files_organizer/data_challenge_to_RTModel.py
jasmine/files_organizer/ephemeris_new.py
jasmine/files_organizer/gulls_rges_to_RTModel.py
jasmine/files_organizer/moa9yr_to_RTModel.py
jasmine/files_organizer/moa_ian_reduced_to_RTModel.py
jasmine/files_organizer/new_data_files_for_pylima.py
jasmine/files_organizer/new_gulls_rges_to_RTModel.py
jasmine/files_organizer/new_gulls_rges_to_RTModel_20k_minus_sample.py
jasmine/files_organizer/new_gulls_rges_to_RTModel_ephemeris.py
jasmine/files_organizer/new_gulls_sample_prioritizer.py
jasmine/files_organizer/ra_and_dec_conversions.py
jasmine/initial_condition_grid_search/__init__.py
jasmine_astro-0.3.0.dist-info/METADATA
jasmine_astro-0.3.0.dist-info/WHEEL
jasmine_astro-0.3.0.dist-info/licenses/LICENSE
jasmine_astro-0.3.0.dist-info/RECORD
