Metadata-Version: 2.4
Name: jasmine-astro
Version: 0.3.0
Summary: JASMINE: Joint Analysis of Simulations for Microlensing INterest Events'
Project-URL: Homepage, https://github.com/stelais/jasmine
Author: Stela IS, Jon H, CR, JASMINE authors
Author-email: Stela IS <stela.ishitanisilva@nasa.gov>
License-Expression: MIT
License-File: LICENSE
Requires-Python: >=3.10
Requires-Dist: astropy>=6.1.0
Requires-Dist: bokeh==3.4.1
Requires-Dist: ipykernel>=6.29.4
Requires-Dist: joblib>=1.4.2
Requires-Dist: jplephem>=2.22
Requires-Dist: jupyter>=1.0.0
Requires-Dist: matplotlib>=3.8.4
Requires-Dist: moana-astro>=0.3.0
Requires-Dist: notebook>=7.1.3
Requires-Dist: pandas>=2.1.4
Requires-Dist: rtmodel>=2.4.0
Requires-Dist: vbmicrolensing>=4.1.0
